dbbpy_testing/__init__.py
dbbpy_testing/compile.py
dbbpy_testing-0.1.5.dist-info/METADATA
dbbpy_testing-0.1.5.dist-info/WHEEL
dbbpy_testing-0.1.5.dist-info/entry_points.txt
dbbpy_testing-0.1.5.dist-info/RECORD
